{
  "name": "player",
  "base": "PersistedModel",
  "idInjection": true,
  "options": {
    "validateUpsert": true
  },
  "properties": {
    "displayName": {
      "type": "string",
      "required": true
    },
    "email": {
      "type": "string",
      "required": true
    },
    "playingState": {
      "type": "string",
      "required": true,
      "default": "inactive"
    },
    "avatar": {
      "type": "string"
    },
    "key": {
      "type": "string"
    },
    "opponent": {
      "type": "string"
    },
    "ladderRank": {
      "type": "number"
    },
    "streak": {
      "type": "array"
    }
  },
  "validations": [],
  "relations": {},
  "methods": {}
}
